protectai/__init__.py
protectai/protectai.py
protectai-1.0.3.dist-info/LICENSE.txt
protectai-1.0.3.dist-info/METADATA
protectai-1.0.3.dist-info/WHEEL
protectai-1.0.3.dist-info/top_level.txt
protectai-1.0.3.dist-info/RECORD
