Metadata-Version: 2.1
Name: protectai
Version: 1.0.3
Summary: Simulation of protecting AI model from poisoning attack
Author: Dr. Deniz Dahman's
Author-email: dahmansphi@gmail.com
Project-URL: Source, https://github.com/dahmansphi/protectai
Project-URL: Project, https://dahmansphi.com/protectai
Keywords: Cybersecurity,Machine Learning,Artificial Intelligence,Poisoning attack
Classifier: Development Status :: 3 - Alpha
Classifier: Intended Audience :: Developers
Classifier: Topic :: Software Development :: Build Tools
Classifier: License :: OSI Approved :: MIT License
Classifier: Programming Language :: Python :: 3
Requires-Python: >=3.9
License-File: LICENSE.txt
